fastapi_boilerplate/.gitignore
fastapi_boilerplate/Dockerfile
fastapi_boilerplate/__init__.py
fastapi_boilerplate/app/__init__.py
fastapi_boilerplate/app/v1/__init__.py
fastapi_boilerplate/app/v1/health/__init__.py
fastapi_boilerplate/app/v1/health/router.py
fastapi_boilerplate/app/views.py
fastapi_boilerplate/core/__init__.py
fastapi_boilerplate/core/factory.py
fastapi_boilerplate/docker-compose.yml
fastapi_boilerplate/pyproject.toml
fastapi_boilerplate/server.py
fastapi_boilerplate/settings/__init__.py
fastapi_boilerplate/settings/config.py
fastapi_speedy/__init__.py
fastapi_speedy/create_app.py
fastapi_speedy-0.1.12.dist-info/METADATA
fastapi_speedy-0.1.12.dist-info/WHEEL
fastapi_speedy-0.1.12.dist-info/entry_points.txt
fastapi_speedy-0.1.12.dist-info/RECORD
