Metadata-Version: 2.1
Name: fastapi-speedy
Version: 0.1.12
Summary: 
Author: Ali Heydarli
Author-email: ali@getwhelp.com
Requires-Python: >=3.11,<4.0
Classifier: Programming Language :: Python :: 3
Classifier: Programming Language :: Python :: 3.11
Requires-Dist: click (>=8.0.0,<9.0.0)
